arvados_cwl/__init__.py
arvados_cwl/_version.py
arvados_cwl/arv-cwl-schema-v1.0.yml
arvados_cwl/arv-cwl-schema-v1.1.yml
arvados_cwl/arv-cwl-schema-v1.2.yml
arvados_cwl/arvcontainer.py
arvados_cwl/arvdocker.py
arvados_cwl/arvtool.py
arvados_cwl/arvworkflow.py
arvados_cwl/context.py
arvados_cwl/done.py
arvados_cwl/executor.py
arvados_cwl/fsaccess.py
arvados_cwl/pathmapper.py
arvados_cwl/perf.py
arvados_cwl/runner.py
arvados_cwl/util.py
arvados_cwl_runner-3.2.0.data/data/share/doc/arvados-cwl-runner/LICENSE-2.0.txt
arvados_cwl_runner-3.2.0.data/data/share/doc/arvados-cwl-runner/README.rst
arvados_cwl_runner-3.2.0.dist-info/licenses/LICENSE-2.0.txt
arvados_cwl_runner-3.2.0.dist-info/METADATA
arvados_cwl_runner-3.2.0.dist-info/WHEEL
arvados_cwl_runner-3.2.0.dist-info/entry_points.txt
arvados_cwl_runner-3.2.0.dist-info/top_level.txt
arvados_cwl_runner-3.2.0.dist-info/RECORD
