Metadata-Version: 2.4
Name: arvados-cwl-runner
Version: 3.2.0
Summary: Arvados Common Workflow Language runner
Author-email: Arvados <info@arvados.org>
License-Expression: Apache-2.0
Project-URL: Homepage, https://arvados.org
Project-URL: Documentation, https://doc.arvados.org
Project-URL: Repository, https://git.arvados.org/arvados.git
Project-URL: Issues, https://dev.arvados.org/projects/arvados/issues
Project-URL: Changelog, https://arvados.org/releases/
Classifier: Development Status :: 5 - Production/Stable
Classifier: Environment :: Console
Classifier: Intended Audience :: Science/Research
Classifier: Operating System :: POSIX
Classifier: Programming Language :: Python :: 3
Classifier: Programming Language :: Python :: 3.10
Classifier: Programming Language :: Python :: 3.11
Classifier: Programming Language :: Python :: 3.12
Classifier: Programming Language :: Python :: 3.13
Classifier: Topic :: Scientific/Engineering :: Bio-Informatics
Requires-Python: ~=3.10
License-File: LICENSE-2.0.txt
Requires-Dist: arvados-python-client==3.2.0
Requires-Dist: crunchstat_summary==3.2.0
Requires-Dist: cwltool==3.1.20240508115724
Requires-Dist: schema-salad==8.5.20240503091721
Requires-Dist: ciso8601>=2.0.0
Dynamic: license-file
Dynamic: requires-dist
